tdp_core/.gitignore
tdp_core/__init__.py
tdp_core/__main__.py
tdp_core/db.py
tdp_core/dbview.py
tdp_core/dev_app.py
tdp_core/formatter.py
tdp_core/graph.py
tdp_core/mapping_table.py
tdp_core/proxy.py
tdp_core/settings.py
tdp_core/sql.py
tdp_core/sql_filter.py
tdp_core/storage.py
tdp_core/swagger.py
tdp_core/utils.py
tdp_core/dataset/__init__.py
tdp_core/dataset/dataset.py
tdp_core/dataset/dataset_api.py
tdp_core/dataset/dataset_def.py
tdp_core/dataset/graph/__init__.py
tdp_core/dataset/graph/graph.py
tdp_core/dataset/graph/graph_api.py
tdp_core/dataset/graph/graph_parser.py
tdp_core/encoder/__init__.py
tdp_core/encoder/bytes_to_string_encoder.py
tdp_core/encoder/json_encoder.py
tdp_core/encoder/set_encoder.py
tdp_core/server/__init__.py
tdp_core/server/main.py
tdp_core/swagger/db.yml
tdp_core/swagger/proxy.yml
tdp_core/swagger/storage.yml
tdp_core/swagger/swagger.yml
tdp_core/swagger/view.tmpl.yml
tdp_core/tests/__init__.py
tdp_core/tests/conftest.py
tdp_core/tests/test_custom_encoders.py
tdp_core/tests/test_main_app.py
tdp_core/tests/fixtures/__init__.py
tdp_core/tests/fixtures/app.py
tdp_core-27.0.0.dist-info/LICENSE
tdp_core-27.0.0.dist-info/METADATA
tdp_core-27.0.0.dist-info/WHEEL
tdp_core-27.0.0.dist-info/entry_points.txt
tdp_core-27.0.0.dist-info/top_level.txt
tdp_core-27.0.0.dist-info/RECORD
