Metadata-Version: 2.2
Name: tdp_core
Version: 27.0.0
Summary: Target discovery platform for exploring rankings of genes, disease models, and other entities.
Home-page: https://www.datavisyn.io
Author: datavisyn GmbH
Author-email: contact@datavisyn.io
License: BSD-3-Clause
Classifier: Intended Audience :: Developers
Classifier: Operating System :: OS Independent
Classifier: License :: OSI Approved :: BSD License
Classifier: Programming Language :: Python
Classifier: Programming Language :: Python :: 3.10
Requires-Python: >=3.10
License-File: LICENSE
Requires-Dist: flask-swagger-ui==3.36.0
Requires-Dist: Pillow==9.3.0
Requires-Dist: pymongo~=3.11.1
Requires-Dist: python-memcached==1.59
Requires-Dist: visyn_core<18.0.0,>=17.0.0
Requires-Dist: yamlreader==3.0.4
Provides-Extra: develop
Requires-Dist: black~=22.12.0; extra == "develop"
Requires-Dist: pyright==1.1.308; extra == "develop"
Requires-Dist: pytest-runner~=6.0.0; extra == "develop"
Requires-Dist: pytest~=7.2.0; extra == "develop"
Requires-Dist: ruff==0.0.218; extra == "develop"
Dynamic: author
Dynamic: author-email
Dynamic: classifier
Dynamic: description
Dynamic: description-content-type
Dynamic: home-page
Dynamic: keywords
Dynamic: license
Dynamic: provides-extra
Dynamic: requires-dist
Dynamic: requires-python
Dynamic: summary
